aoti/__init__.py
aoti-0.1.0.dist-info/METADATA
aoti-0.1.0.dist-info/WHEEL
aoti-0.1.0.dist-info/RECORD
