Metadata-Version: 2.1
Name: aoti
Version: 0.1.0
Summary: Hugging Face ahead-of-time PyTorch compilation
Author: cbensimon
Author-email: charles@huggingface.co
Requires-Python: >=3.10,<4.0
Classifier: Programming Language :: Python :: 3
Classifier: Programming Language :: Python :: 3.10
Classifier: Programming Language :: Python :: 3.11
Classifier: Programming Language :: Python :: 3.12
